.gitignore
.travis-deploy-doc.sh
.travis-install.sh
.travis-test.sh
.travis.yml
CHANGES
Dockerfile
LICENSE
MANIFEST.in
Makefile
README.rst
VERSION
demo.ipynb
requirements.txt
setup.cfg
setup.py
docs/Makefile
docs/source/algebra.rst
docs/source/conf.py
docs/source/conf.py.bak
docs/source/index.rst
docs/source/tmplist.rst
docs/source/todo.rst
zetalib/__init__.py
zetalib/abstract.py
zetalib/addmany.c
zetalib/addmany.pyx
zetalib/algebra.py
zetalib/ask.py
zetalib/common.py
zetalib/convex.py
zetalib/crunch.c
zetalib/cycrat.py
zetalib/examples.py
zetalib/laurent.py
zetalib/maple.cpp
zetalib/p-adic-examples.json
zetalib/reps.py
zetalib/smurf.py
zetalib/subobjects.py
zetalib/surf.py
zetalib/tmplist.py
zetalib/toric.py
zetalib/torus.py
zetalib/triangulate.py
zetalib/util.py
zetalib.egg-info/PKG-INFO
zetalib.egg-info/SOURCES.txt
zetalib.egg-info/dependency_links.txt
zetalib.egg-info/requires.txt
zetalib.egg-info/top_level.txt