Metadata-Version: 1.1
Name: zetalib
Version: 0.4.5
Summary: computing zeta functions of groups, algebras, and modules
Home-page: https://gitlab.com/mathzeta2/zetalib
Author: Tobias Rossmann, Tomer Bauer
Author-email: UNKNOWN
License: GPLv3+
Keywords: SageMath packaging
Platform: UNKNOWN
Classifier: Development Status :: 4 - Beta
Classifier: Intended Audience :: Science/Research
Classifier: Topic :: Software Development :: Build Tools
Classifier: Topic :: Scientific/Engineering :: Mathematics
Classifier: License :: OSI Approved :: GNU General Public License v3 or later (GPLv3+)
Classifier: Programming Language :: Python :: 2.7
Classifier: Programming Language :: Python :: 3
